{
  "chapter": "هود",
  "text": "من دونه فكيدونى جميعا ثم لا تنظرون",
  "translations": [
    {
      "translation": "So scheme against me, all of you together, and then grant me no respite.",
      "language": "english",
      "translator": ""
    },
    {
      "translation": "Apart from Him. Contrive against me as much as you like, and give me no respite.\n",
      "language": "english",
      "translator": ""
    },
    {
      "translation": "others than Him in His divinity. So conspire against me, all of you, and give me no respite.\n",
      "language": "english",
      "translator": ""
    },
    {
      "translation": "with the idols that you worship besides God. So plan against me without delay.\n",
      "language": "english",
      "translator": ""
    },
    {
      "translation": "“Besides Him – therefore all of you scheme against me and do not give me respite.”\n",
      "language": "english",
      "translator": ""
    },
    {
      "translation": "Besides Him (Allah). So plot against me, all of you, and give me no respite.\"\n",
      "language": "english",
      "translator": ""
    },
    {
      "translation": "Besides Him, therefore scheme against me all together; then give me no respite:\n",
      "language": "english",
      "translator": ""
    },
    {
      "translation": "apart from Him; so try your guile on me, all together, then you shall give me no respite.\n",
      "language": "english",
      "translator": ""
    },
    {
      "translation": "Beside Him. So (try to) circumvent me, all of you, give me no respite.\n",
      "language": "english",
      "translator": ""
    },
    {
      "translation": "So scheme against me, all of you together, and then grant me no respite.\n",
      "language": "english",
      "translator": ""
    },
    {
      "translation": "Beside Him, so plot against me all tcgether, and then respite me not.\n",
      "language": "english",
      "translator": ""
    },
    {
      "translation": "besides Him. Now try out your stratagems against me, together, without granting me any respite.\n",
      "language": "english",
      "translator": ""
    },
    {
      "translation": "Other gods as partners! so scheme (your worst) against me, all of you, and give me no respite.\n",
      "language": "english",
      "translator": ""
    },
    {
      "translation": "With Him (Allah). So plot against me, all of you, and give me no respite.\n",
      "language": "english",
      "translator": ""
    },
    {
      "translation": "other than Him, so all of you, scheme against me, then you shall give me no respite.\n",
      "language": "english",
      "translator": ""
    },
    {
      "translation": "Besides Him. So scheme against me, all of you, and do not hesitate.\n",
      "language": "english",
      "translator": ""
    },
    {
      "translation": "Other than Him. So plot against me all together; then do not give me respite.\n",
      "language": "english",
      "translator": ""
    },
    {
      "translation": "[11:55] beside Him; so plot against me, devise ways to destroy me, all together, you and your graven images, then give me no respite, grant me [no] reprieve.\n",
      "language": "english",
      "translator": ""
    }
  ],
  "commentaries": [
    {
      "author": "ابن عباس",
      "year": "68",
      "text": "",
      "translations": [
        {
          "translation": "And I am innocent of your worship of these idols (Beside Him. So (try to) circumvent me) work to destroy me, you and your idols, (all of you, give me no respite) neither delay nor pity on me.\n",
          "language": "english",
          "translator": "Mr. Mokrane Guezzou"
        }
      ]
    },
    {
      "author": "زيد بن علي",
      "year": "120",
      "text": "\n",
      "translations": []
    },
    {
      "author": "ابن عربي",
      "year": "638",
      "text": "\n",
      "translations": []
    },
    {
      "author": "الجيلاني",
      "year": "713",
      "text": "",
      "translations": []
    },
    {
      "author": "ابن عجيبة",
      "year": "1224",
      "text": "\n  { قال } هود عليه السلام: { إني أُشهد الله } على براءتي من شرككم، { واشهدوا أني بريء مما تُشركون من دونه فكيدوني } أي: اقصدوا كيدي وهلاكي، { جميعاً } ، أنتم وشركاؤكم، { ثم لا تنظرون } لا تؤخرون ساعة\n وهذا من جملة معجزاته، فإن مواجهة الواحد الجم الغفير من الجبابرة، والفتاك العِطاش إلى إراقة دمه، بهذا الكلام، ليس إلا لتيقنه بالله، ومنعُهم من إضراره ليس إلا لعصمته إياه\n ولذلك عقبه بقوله: { إني توكلتُ على الله ربي وربكم } ، فهو تقرير له\n والمعنى: أنكم وإن بذلتم غاية وسعكم لم تضروني فإني متوكل على الله، واثق بكلاءته، وهو مالكي ومالككم، لا يحيق بي ما لم يُرده، ولا تقدرون على ما لم يُقدره",
      "translations": []
    }
  ]
}