{
  "chapter": "طه",
  "text": "اننى انا الله لا اله الا انا۠ فاعبدنى واقم الصلوة لذكرى",
  "translations": [
    {
      "translation": "I am Allah. There is no god but Me, so worship Me and establish salat to remember Me.",
      "language": "english",
      "translator": ""
    },
    {
      "translation": "I am God, and there is no god but I, so serve Me, and observe acts of prayer to remember Me.\n",
      "language": "english",
      "translator": ""
    },
    {
      "translation": "Verily I am Allah. There is no god beside Me. So serve Me and establish Prayers to remember Me.\n",
      "language": "english",
      "translator": ""
    },
    {
      "translation": "I Am the only God. Worship Me and be steadfast in prayer to have My name always in your mind.\n",
      "language": "english",
      "translator": ""
    },
    {
      "translation": "“Indeed it is Me, Allah – there is no God except I – therefore worship Me and keep the prayer established for My remembrance.”\n",
      "language": "english",
      "translator": ""
    },
    {
      "translation": "Verily, I am Allah! There is no God but Me, so worship Me, and perform Salah for My remembrance.\"\n",
      "language": "english",
      "translator": ""
    },
    {
      "translation": "Surely I am Allah, there is no god but I, therefore serve Me and keep up prayer for My remembrance:\n",
      "language": "english",
      "translator": ""
    },
    {
      "translation": "Verily I am God; there is no god but I; therefore serve Me, and perform the prayer of My remembrance.\n",
      "language": "english",
      "translator": ""
    },
    {
      "translation": "Lo! I, even I, am Allah, There is no Allah save Me. So serve Me and establish worship for My remembrance.\n",
      "language": "english",
      "translator": ""
    },
    {
      "translation": "I am God. There is no deity save Me; so worship Me alone, and say your prayers in My remembrance.\n",
      "language": "english",
      "translator": ""
    },
    {
      "translation": "Verily I! I am Allah! no God there is butI; so Worship Me, and establish prayer for My remembrance.\n",
      "language": "english",
      "translator": ""
    },
    {
      "translation": "Indeed I am Allah—there is no god except Me. So worship Me, and maintain the prayer for My remembrance.\n",
      "language": "english",
      "translator": ""
    },
    {
      "translation": "Verily, I am Allah: There is no god but I: So serve thou Me (only), and establish regular prayer for celebrating My praise.\n",
      "language": "english",
      "translator": ""
    },
    {
      "translation": "Verily! I am Allah! La ilaha illa Ana (none has the right to be worshipped but I), so worship Me, and perform As-Salat (Iqamat-as-Salat) for My Remembrance.\n",
      "language": "english",
      "translator": ""
    },
    {
      "translation": "Indeed, I am Allah. There is no god except Me. Worship Me, and establish the prayer of My remembrance.\n",
      "language": "english",
      "translator": ""
    },
    {
      "translation": "I—I am God. There is no God but I. So serve Me, and practice the prayer for My remembrance.\n",
      "language": "english",
      "translator": ""
    },
    {
      "translation": "Indeed, I am Allah. There is no deity except Me, so worship Me and establish prayer for My remembrance.\n",
      "language": "english",
      "translator": ""
    },
    {
      "translation": "[20:14] Verily I am God — there is no god except Me. So worship Me and establish prayer for to make remembrance of Me, in it.\n",
      "language": "english",
      "translator": ""
    }
  ],
  "commentaries": [
    {
      "author": "ابن عباس",
      "year": "68",
      "text": "",
      "translations": [
        {
          "translation": "(Lo! I, even I, am Allah. There is no God save Me. serve Me) obey Me (and establish worship for My remembrance) when you forget to perform a prayer, perform it when you do remember.\n",
          "language": "english",
          "translator": "Mr. Mokrane Guezzou"
        }
      ]
    },
    {
      "author": "زيد بن علي",
      "year": "120",
      "text": "\n",
      "translations": []
    },
    {
      "author": "ابن عربي",
      "year": "638",
      "text": "\n",
      "translations": []
    },
    {
      "author": "الجيلاني",
      "year": "713",
      "text": "",
      "translations": []
    },
    {
      "author": "ابن عجيبة",
      "year": "1224",
      "text": "",
      "translations": []
    }
  ]
}