{
  "chapter": "الأحزاب",
  "text": "خلدين فيها ابدا لا يجدون وليا ولا نصيرا",
  "translations": [
    {
      "translation": "where they will remain timelessly, for ever and ever, not finding any protector or any helper.",
      "language": "english",
      "translator": ""
    },
    {
      "translation": "They will live in it for ever, and will find no saviour or helper.\n",
      "language": "english",
      "translator": ""
    },
    {
      "translation": "therein they shall abide for ever. They shall find none to protect or help them.\n",
      "language": "english",
      "translator": ""
    },
    {
      "translation": "wherein they will live forever without being able to find any guardian or helper.\n",
      "language": "english",
      "translator": ""
    },
    {
      "translation": "In which they will remain forever; in it they will find neither a protector nor any supporter.\n",
      "language": "english",
      "translator": ""
    },
    {
      "translation": "Wherein they will abide forever, and they will find neither a a protector nor a helper.\n",
      "language": "english",
      "translator": ""
    },
    {
      "translation": "To abide therein for a long time; they shall not find a protector or a helper.\n",
      "language": "english",
      "translator": ""
    },
    {
      "translation": "therein to dwell for ever; they shall find neither protector nor helper.\n",
      "language": "english",
      "translator": ""
    },
    {
      "translation": "Wherein they will abide for ever. They will find (then) no protecting friend nor helper.\n",
      "language": "english",
      "translator": ""
    },
    {
      "translation": "There they will live forever, and they will find therein neither friend nor helper.\n",
      "language": "english",
      "translator": ""
    },
    {
      "translation": "Abiders therein they shall be for ever, and they shall find neither a protecting friend nor a helper.\n",
      "language": "english",
      "translator": ""
    },
    {
      "translation": "in which they will remain forever, and will not find any guardian or helper.\n",
      "language": "english",
      "translator": ""
    },
    {
      "translation": "To dwell therein for ever: no protector will they find, nor helper.\n",
      "language": "english",
      "translator": ""
    },
    {
      "translation": "Wherein they will abide for ever, and they will find neither a Wali (a protector) nor a helper.\n",
      "language": "english",
      "translator": ""
    },
    {
      "translation": "Living there for ever, they shall neither find a guardian nor a helper.\n",
      "language": "english",
      "translator": ""
    },
    {
      "translation": "Dwelling therein forever, not finding a protector or a savior.\n",
      "language": "english",
      "translator": ""
    },
    {
      "translation": "Abiding therein forever, they will not find a protector or a helper.\n",
      "language": "english",
      "translator": ""
    },
    {
      "translation": "[33:65] to abide, their abiding having been foreordained, therein forever. They shall not find any protector, to preserve them from it, or helper, to ward it off from them.\n",
      "language": "english",
      "translator": ""
    }
  ],
  "commentaries": [
    {
      "author": "ابن عباس",
      "year": "68",
      "text": "",
      "translations": [
        {
          "translation": "Wherein) in the Fire (they will abide for ever) never to die or leave. (They will find (then) no protecting friend) no protector to protect from the Allah's chastisement (nor helper) to spare them from Allah's torment.\n",
          "language": "english",
          "translator": "Mr. Mokrane Guezzou"
        }
      ]
    },
    {
      "author": "زيد بن علي",
      "year": "120",
      "text": "\n",
      "translations": []
    },
    {
      "author": "ابن عربي",
      "year": "638",
      "text": "\n",
      "translations": []
    },
    {
      "author": "الجيلاني",
      "year": "713",
      "text": "\n{ خَالِدِينَ فِيهَآ أَبَداً } لا يتحولون عنها أصلاً لا بأنفسهم ولا بواسطة غيرهم من شفعائهم { لاَّ يَجِدُونَ وَلِيّاً } يولي أمرهم وينقذهم منها { وَلاَ نَصِيراً } [الأحزاب: 65] ينصرهم ويعين عليهم لإخراجهم عنها\n\n\n\n",
      "translations": []
    },
    {
      "author": "ابن عجيبة",
      "year": "1224",
      "text": "\n { لا يجدون وليًّا } يحفظهم، { ولا نصيراً } يمنعهم ويدفع العذاب عنهم، وذلك { يومَ تُقَلَّبُ } أو: واذكر { يومَ تُقَلَّبُ وجوهُهُم في النار } تطوف من جهة إلى جهة، كما ترى البضعة من اللحم تدُور في القِدْرِ إذا غلت\n وخصّت الوجوه لأنها أكرم موضع على الإنسان من جسده\n أو: يكون الوجه كناية عن الجملة\n حال كونهم { يقولون يا ليتنا أطعنا اللهَ وأطعنا الرسولا } في الدنيا، فنتخلص من هذا العذاب، فندّموا حيث لم ينفع الندم",
      "translations": []
    }
  ],
  "most_similar_verses": [
    {
      "verse": "9:22",
      "similarity": 0.6685725581173674
    },
    {
      "verse": "72:23",
      "similarity": 0.5093049478194215
    },
    {
      "verse": "4:122",
      "similarity": 0.44011052024318165
    },
    {
      "verse": "24:17",
      "similarity": 0.40204576537535847
    },
    {
      "verse": "59:11",
      "similarity": 0.3945724584310361
    }
  ]
}