{
  "chapter": "الصافات",
  "text": "فاتوا۟ بكتبكم ان كنتم صدقين",
  "translations": [
    {
      "translation": "Then bring your scripture, if what you say is true.\n",
      "language": "english",
      "translator": ""
    },
    {
      "translation": "Bring your Book, if you are truthful.\n",
      "language": "english",
      "translator": ""
    },
    {
      "translation": "Bring your book if what you say is true.\n",
      "language": "english",
      "translator": ""
    },
    {
      "translation": "“Then bring forth your Book, if you are truthful!”\n",
      "language": "english",
      "translator": ""
    },
    {
      "translation": "Then bring your Book if you are truthful!\n",
      "language": "english",
      "translator": ""
    },
    {
      "translation": "Then bring your book, if you are truthful.\n",
      "language": "english",
      "translator": ""
    },
    {
      "translation": "Bring your Book, if you speak truly!\n",
      "language": "english",
      "translator": ""
    },
    {
      "translation": "Then produce your writ, if ye are truthful.\n",
      "language": "english",
      "translator": ""
    },
    {
      "translation": "Then produce your scriptures, if you are telling the truth.\n",
      "language": "english",
      "translator": ""
    },
    {
      "translation": "Then bring your book, if ye say sooth.\n",
      "language": "english",
      "translator": ""
    },
    {
      "translation": "Then produce your scripture, should you be truthful.\n",
      "language": "english",
      "translator": ""
    },
    {
      "translation": "Then bring ye your Book (of authority) if ye be truthful!\n",
      "language": "english",
      "translator": ""
    },
    {
      "translation": "Then bring your Book if you are truthful!\n",
      "language": "english",
      "translator": ""
    },
    {
      "translation": "Bring your Book, if what you say is true!\n",
      "language": "english",
      "translator": ""
    },
    {
      "translation": "Then bring your book, if you are telling the truth.\n",
      "language": "english",
      "translator": ""
    },
    {
      "translation": "Then produce your scripture, if you should be truthful.\n",
      "language": "english",
      "translator": ""
    },
    {
      "translation": "[37:157] Then produce your scripture, the Torah, and show Me this [as it is mentioned] in it, if you are being truthful, about this statement of yours.\n",
      "language": "english",
      "translator": ""
    }
  ],
  "commentaries": [
    {
      "author": "ابن عباس",
      "year": "68",
      "text": "",
      "translations": [
        {
          "translation": "(Then produce your writ, if ye are truthful) that the angels are Allah's daughters.\n",
          "language": "english",
          "translator": "Mr. Mokrane Guezzou"
        }
      ]
    },
    {
      "author": "زيد بن علي",
      "year": "120",
      "text": "\n",
      "translations": []
    },
    {
      "author": "ابن عربي",
      "year": "638",
      "text": "\n",
      "translations": []
    },
    {
      "author": "الجيلاني",
      "year": "713",
      "text": "\n{ فَأْتُواْ بِكِتَابِكُمْ } النازل عليكم من قبل الحق المثبت لدعواكم { إِن كُنتُمْ صَادِقِينَ } [الصافات: 157]\n\n\n\n",
      "translations": []
    },
    {
      "author": "ابن عجيبة",
      "year": "1224",
      "text": "\n",
      "translations": []
    }
  ]
}