{
  "chapter": "الصافات",
  "text": "اذ ابق الى الفلك المشحون",
  "translations": [
    {
      "translation": "When he fled on the laden ship,\n",
      "language": "english",
      "translator": ""
    },
    {
      "translation": "Call to mind when he fled to the laden ship,\n",
      "language": "english",
      "translator": ""
    },
    {
      "translation": "He abandoned his people\n",
      "language": "english",
      "translator": ""
    },
    {
      "translation": "When he left towards the laden ship.\n",
      "language": "english",
      "translator": ""
    },
    {
      "translation": "When he ran to the laden ship:\n",
      "language": "english",
      "translator": ""
    },
    {
      "translation": "When he ran away to a ship completely laden,\n",
      "language": "english",
      "translator": ""
    },
    {
      "translation": "when he ran away to the laden ship\n",
      "language": "english",
      "translator": ""
    },
    {
      "translation": "When he fled unto the laden ship,\n",
      "language": "english",
      "translator": ""
    },
    {
      "translation": "He fled to the overloaded ship.\n",
      "language": "english",
      "translator": ""
    },
    {
      "translation": "Recall what time he ran away Unto a laden ship.\n",
      "language": "english",
      "translator": ""
    },
    {
      "translation": "When he absconded toward the laden ship,\n",
      "language": "english",
      "translator": ""
    },
    {
      "translation": "When he ran away (like a slave from captivity) to the ship (fully) laden,\n",
      "language": "english",
      "translator": ""
    },
    {
      "translation": "When he ran to the laden ship,\n",
      "language": "english",
      "translator": ""
    },
    {
      "translation": "He ran away to the laden ship,\n",
      "language": "english",
      "translator": ""
    },
    {
      "translation": "When he fled to the laden boat.\n",
      "language": "english",
      "translator": ""
    },
    {
      "translation": "[Mention] when he ran away to the laden ship.\n",
      "language": "english",
      "translator": ""
    },
    {
      "translation": "[37:140] when he fled to the laden ship — after he became furious with his people, as the chastisement which he had promised them did not come down on them; so he boarded the ship, which then stopped out in the deep sea. The seamen said, ‘There is a runaway slave here [upon this ship] who has fled from his master: a casting of lots should expose him!’\n",
      "language": "english",
      "translator": ""
    }
  ],
  "commentaries": [
    {
      "author": "ابن عباس",
      "year": "68",
      "text": "",
      "translations": [
        {
          "translation": "(When he fled) from his folk; and it is said: when he abandoned his folk (unto the laden ship) which was about to sail,\n",
          "language": "english",
          "translator": "Mr. Mokrane Guezzou"
        }
      ]
    },
    {
      "author": "زيد بن علي",
      "year": "120",
      "text": "\n",
      "translations": []
    },
    {
      "author": "ابن عربي",
      "year": "638",
      "text": "\n",
      "translations": []
    },
    {
      "author": "الجيلاني",
      "year": "713",
      "text": "\nاذكر يا أكمل الرسل وقت { إِذْ أَبَقَ } وهرب من نزول العذاب الموعود على قومه حين دعاهم إلى الإيمان والتوبة، فلم يجيبوا له ولم يقبلوا منه دعوته، فدعا عليهم، وبعدما قرب حلول العذاب عليهم\n خرج من بينهم هارباً، حتى لا يحلقه ما يحلقهم، فلما وصل البحر ركب { إِلَى ٱلْفُلْكِ ٱلْمَشْحُونِ } [الصافات: 140] المملوء من الناس والأحمال والأثقال، فاحتسبت السفينة على أهلها فاضطربوا، فقال البحارون: إن في السفينة عبداً آبقاً، فبادروا إلى القرعة ما على ما هو عادتهم في أمثاله، وبعد خروج القرعة باسم واحد من أهلها، طرحوه في الماء فأخذت في الجري والذهاب\n\n\n\n",
      "translations": []
    },
    {
      "author": "ابن عجيبة",
      "year": "1224",
      "text": "\n رُوي أنه لمَّا فرَّ عنهم، وقف في مكان ينتظر نزول العذاب بهم، وكان يُحب ذلك لتكذيبهم إياه، فلما رأوا مخايل العذاب تابوا وخرجوا إلى الصحراء، يجأرون إلى الله تعالى، فكشف عنهم، فلما رأى يونس العذابَ انكشف عنهم، كره أن يرجع إليهم، فركب البحر، فأوى { إِلى الفُلْكِ المشحونِ }: المملوء بالناس والمتاع، فلما ركب معهم وقفت السفينة، فقالوا: هاهنا عبد آبق من سيده",
      "translations": []
    }
  ]
}