{
  "chapter": "الصافات",
  "text": "طلعها كانه رءوس الشيطين",
  "translations": [
    {
      "translation": "Its fruits are just like the heads of shaytans.",
      "language": "english",
      "translator": ""
    },
    {
      "translation": "Its spathes are like the prickly pear.\n",
      "language": "english",
      "translator": ""
    },
    {
      "translation": "Its spathes are like the heads of satans.\n",
      "language": "english",
      "translator": ""
    },
    {
      "translation": "and its fruits are like the heads of devils.\n",
      "language": "english",
      "translator": ""
    },
    {
      "translation": "Its fruit like the heads of demons.\n",
      "language": "english",
      "translator": ""
    },
    {
      "translation": "The shoots of its fruit stalks are like the heads of Shayatin.\n",
      "language": "english",
      "translator": ""
    },
    {
      "translation": "Its produce is as it were the heads of the serpents.\n",
      "language": "english",
      "translator": ""
    },
    {
      "translation": "its spathes are as the heads of Satans,\n",
      "language": "english",
      "translator": ""
    },
    {
      "translation": "Its crop is as it were the heads of devils\n",
      "language": "english",
      "translator": ""
    },
    {
      "translation": "and its fruits are like devils' heads.\n",
      "language": "english",
      "translator": ""
    },
    {
      "translation": "The fruit thereof is as though the hoods of the serpents.\n",
      "language": "english",
      "translator": ""
    },
    {
      "translation": "Its spathes are as if they were devils’ heads.\n",
      "language": "english",
      "translator": ""
    },
    {
      "translation": "The shoots of its fruit-stalks are like the heads of devils:\n",
      "language": "english",
      "translator": ""
    },
    {
      "translation": "The shoots of its fruit-stalks are like the heads of Shayatin (devils);\n",
      "language": "english",
      "translator": ""
    },
    {
      "translation": "its spathes are like the heads of satans\n",
      "language": "english",
      "translator": ""
    },
    {
      "translation": "Its fruits are like the devils’ heads.\n",
      "language": "english",
      "translator": ""
    },
    {
      "translation": "Its emerging fruit as if it was heads of the devils.\n",
      "language": "english",
      "translator": ""
    },
    {
      "translation": "[37:65] Its spathes, likened to the spathes of a date-palm, are like the heads of devils, [as] vile-looking snakes.\n",
      "language": "english",
      "translator": ""
    }
  ],
  "commentaries": [
    {
      "author": "ابن عباس",
      "year": "68",
      "text": "",
      "translations": [
        {
          "translation": "(Its crop) its fruit (is as it were the heads of devils) the heads of snakes which resemble devils. This kind of snakes is found near Yemen.\n",
          "language": "english",
          "translator": "Mr. Mokrane Guezzou"
        }
      ]
    },
    {
      "author": "زيد بن علي",
      "year": "120",
      "text": "\nوقوله تعالى: { طَلْعُهَا كَأَنَّهُ رُءُوسُ ٱلشَّيَاطِينِ } وهو نبتٌ قَبيحُ المَنظرِ\n\n",
      "translations": []
    },
    {
      "author": "ابن عربي",
      "year": "638",
      "text": "\n",
      "translations": []
    },
    {
      "author": "الجيلاني",
      "year": "713",
      "text": "\n{ طَلْعُهَا } أي: ثمرتها التي تطلع منها أو تحصل { كَأَنَّهُ رُءُوسُ ٱلشَّيَاطِينِ } [الصافات: 65] في القبح والهجنة، هذا من قبيل التشبيه المحسوس بالمتخيل، كتشيبه الطيور الحسنة بالملائكة؛ يعني: يستكره من رؤيتها الطباع استكراهها من رءوس المردة من الجن المصورة على أقبح الصور وأهولها\n\n\n\n",
      "translations": []
    },
    {
      "author": "ابن عجيبة",
      "year": "1224",
      "text": "\n { طَلْعُها } أي: حملها { كأنه رؤوس الشياطين } الطلع للنخلة، فاستعير لما يطلع من شجرة الزقوم من حملها، وشُبِّه برؤوس الشياطين للدلالة على تناهيه في الكراهة، وقُبح المنظر لأن الشيطان مكروه مستقبَح في طباع الناس لاعتقادهم أنه شرّ محض\n وقيل: الشياطين: حيَّات هائلة، قبيحة المنظر، لها أعراف يقال لها شياطين\n وقيل: شبه بما استقر في النفوس من كراهة رؤوس الشياطين وقُبحها، وإن كانت لا ترى، كما شبهوا سنان الرماح بأنياب أغوال، كما قال امرؤ القيس:\n",
      "translations": []
    }
  ],
  "most_similar_verses": [
    {
      "verse": "37:54",
      "similarity": 0.4842676076889488
    },
    {
      "verse": "37:55",
      "similarity": 0.40841515476387785
    },
    {
      "verse": "97:5",
      "similarity": 0.39790959888001187
    },
    {
      "verse": "19:78",
      "similarity": 0.3912226253118274
    },
    {
      "verse": "104:7",
      "similarity": 0.39014737450636644
    }
  ]
}