{
  "chapter": "آل عمران",
  "text": "ذريةۢ بعضها منۢ بعض والله سميع عليم",
  "translations": [
    {
      "translation": "Allah chose Adam and Nuh and the family of Ibrahim and the family of 'Imran over all other beings -",
      "language": "english",
      "translator": ""
    },
    {
      "translation": "They were descendants of one another; and God hears all and knows everything.\n",
      "language": "english",
      "translator": ""
    },
    {
      "translation": "(for His messengership) - a people alike and the seed of one another. Allah is All-Hearing, All-Knowing.\n",
      "language": "english",
      "translator": ""
    },
    {
      "translation": "They were the offspring of one another. God is All-hearing and All-seeing.\n",
      "language": "english",
      "translator": ""
    },
    {
      "translation": "They are the descendants one of another; and Allah is the All Hearing, the All Knowing.\n",
      "language": "english",
      "translator": ""
    },
    {
      "translation": "Offspring, one of the other, and Allah is All-Hearer, All-Knower.\n",
      "language": "english",
      "translator": ""
    },
    {
      "translation": "Offspring one of the other; and Allah is Hearing, Knowing.\n",
      "language": "english",
      "translator": ""
    },
    {
      "translation": "seed of one another; God hears, and knows.\n",
      "language": "english",
      "translator": ""
    },
    {
      "translation": "They were descendants one of another. Allah is Hearer, Knower.\n",
      "language": "english",
      "translator": ""
    },
    {
      "translation": "They are the offspring of one another. God hears all and knows all.\n",
      "language": "english",
      "translator": ""
    },
    {
      "translation": "Progeny, one of the other, and Allah is Hearing, Knowing.\n",
      "language": "english",
      "translator": ""
    },
    {
      "translation": "some of them are descendants of the others, and Allah is all-hearing, all-knowing.\n",
      "language": "english",
      "translator": ""
    },
    {
      "translation": "Offspring, one of the other: And Allah heareth and knoweth all things.\n",
      "language": "english",
      "translator": ""
    },
    {
      "translation": "Offspring, one of the other, and Allah is the All-Hearer, All-Knower.\n",
      "language": "english",
      "translator": ""
    },
    {
      "translation": "They were the offspring of one another. Allah is Hearing, and Knowing.\n",
      "language": "english",
      "translator": ""
    },
    {
      "translation": "Offspring one of the other. God is Hearer and Knower.\n",
      "language": "english",
      "translator": ""
    },
    {
      "translation": "Descendants, some of them from others. And Allah is Hearing and Knowing.\n",
      "language": "english",
      "translator": ""
    },
    {
      "translation": "[3:34] the seed of one, offspring from, another, of them; God is Hearer, Knower.\n",
      "language": "english",
      "translator": ""
    }
  ],
  "commentaries": [
    {
      "author": "ابن عباس",
      "year": "68",
      "text": "",
      "translations": [
        {
          "translation": "(They were descendants one of another) some follow the religion of others and the offspring of some are the descendents of others. (Allah is Hearer) of what the Jews say: that they are Allah's children and beloved ones and that they follow His religion, (Knower) of their punishment and of whom is following His religion.\n",
          "language": "english",
          "translator": "Mr. Mokrane Guezzou"
        }
      ]
    },
    {
      "author": "زيد بن علي",
      "year": "120",
      "text": "\n",
      "translations": []
    },
    {
      "author": "ابن عربي",
      "year": "638",
      "text": "\n",
      "translations": []
    },
    {
      "author": "الجيلاني",
      "year": "713",
      "text": "\nثم إن اصطفاء الله إياهم ليس مخصوصاً بهم بل اصطفى منهم { ذُرِّيَّةً } أخلافاً فضلاء { بَعْضُهَا مِن بَعْضٍ } أي: أعلى ربتة من بعض في الفضيلة كما قال سبحانه: { تِلْكَ ٱلرُّسُلُ فَضَّلْنَا بَعْضَهُمْ عَلَىٰ بَعْضٍ } [البقرة: 253] { وَٱللَّهُ } المحيط بسرائر عباده المتوجهين نحو بابه { سَمِيعٌ } لمناجاتهم الصادرة من ألسنة استعدادتهم { عَلِيمٌ } [آل عمران: 34] بما يليق لهم من المراتب العلية\n\n\n\n",
      "translations": []
    },
    {
      "author": "ابن عجيبة",
      "year": "1224",
      "text": "\nقلت: { ذرية }: حال، أبو بدل من الآلين، أو من نوح، أي: أنهم ذرية واحد متشعبة بعضها من بعض",
      "translations": []
    }
  ],
  "most_similar_verses": [
    {
      "verse": "14:40",
      "similarity": 0.5526061363452534
    },
    {
      "verse": "99:7",
      "similarity": 0.4429082399561191
    },
    {
      "verse": "37:77",
      "similarity": 0.44092161930849855
    },
    {
      "verse": "17:3",
      "similarity": 0.38703264886234734
    },
    {
      "verse": "13:38",
      "similarity": 0.38627658303880646
    }
  ]
}