{
  "chapter": "آل عمران",
  "text": "فان تولوا۟ فان الله عليمۢ بالمفسدين",
  "translations": [
    {
      "translation": "And if they turn away, Allah knows the corrupters.",
      "language": "english",
      "translator": ""
    },
    {
      "translation": "If they turn away (remember) God knows the mischief-mongers.\n",
      "language": "english",
      "translator": ""
    },
    {
      "translation": "And if they turn their backs, truly Allah knows those who cause mischief.\n",
      "language": "english",
      "translator": ""
    },
    {
      "translation": "If they turn away (from the Truth, let it be known that) God knows well the evil-doers.\n",
      "language": "english",
      "translator": ""
    },
    {
      "translation": "So if they turn away, then indeed Allah knows those who cause turmoil.\n",
      "language": "english",
      "translator": ""
    },
    {
      "translation": "And if they turn away, then surely, Allah is All-Aware of those who do mischief.\n",
      "language": "english",
      "translator": ""
    },
    {
      "translation": "But if they turn back, then surely Allah knows the mischief-makers.\n",
      "language": "english",
      "translator": ""
    },
    {
      "translation": "And if they turn their backs, assuredly God knows the workers of corruption.\n",
      "language": "english",
      "translator": ""
    },
    {
      "translation": "And if they turn away, then lo! Allah is Aware of (who are) the corrupters.\n",
      "language": "english",
      "translator": ""
    },
    {
      "translation": "And if they turn away, God knows well the evil-doers.\n",
      "language": "english",
      "translator": ""
    },
    {
      "translation": "But if they turn away, then Allah is Knower of the corrupters.\n",
      "language": "english",
      "translator": ""
    },
    {
      "translation": "But if they turn away, indeed Allah knows best the agents of corruption.\n",
      "language": "english",
      "translator": ""
    },
    {
      "translation": "But if they turn back, Allah hath full knowledge of those who do mischief.\n",
      "language": "english",
      "translator": ""
    },
    {
      "translation": "And if they turn away (and do not accept these true proofs and evidences), then surely, Allah is All-Aware of those who do mischief.\n",
      "language": "english",
      "translator": ""
    },
    {
      "translation": "If they turn away, Allah knows the evildoers.\n",
      "language": "english",
      "translator": ""
    },
    {
      "translation": "But if they turn away—God knows the corrupt.\n",
      "language": "english",
      "translator": ""
    },
    {
      "translation": "But if they turn away, then indeed - Allah is Knowing of the corrupters.\n",
      "language": "english",
      "translator": ""
    },
    {
      "translation": "[3:63] And if they turn their backs, rejecting faith, assuredly God knows the agents of corruption, and will requite them (here the [third person] pronominalisation has been replaced with the overt noun [al-mufsidūn, ‘the agents of corruption’]).\n",
      "language": "english",
      "translator": ""
    }
  ],
  "commentaries": [
    {
      "author": "ابن عباس",
      "year": "68",
      "text": "",
      "translations": [
        {
          "translation": "(And if they turn away) from joining the Prophet (pbuh) in invoking Allah's curse on those who lie about Him regarding Jesus (then Lo! Allah is Aware of (who are) the corrupters) i.e. the Christians of Najran.\n",
          "language": "english",
          "translator": "Mr. Mokrane Guezzou"
        }
      ]
    },
    {
      "author": "زيد بن علي",
      "year": "120",
      "text": "\nوقوله تعالى: { فَإِن تَوَلَّوْاْ } معناهُ كَفَرُوا\n\n",
      "translations": []
    },
    {
      "author": "ابن عربي",
      "year": "638",
      "text": "\n",
      "translations": []
    },
    {
      "author": "الجيلاني",
      "year": "713",
      "text": "\n{ فَإِن تَوَلَّوْاْ } أعرضوا عن الحق بعدما ظهر دلالته وشواهده أعرض عنهم ولا تجادل معهم { فَإِنَّ ٱللَّهَ } المنتقم لمن أعرض عن سبيله { عَلِيمٌ بِٱلْمُفْسِدِينَ } [آل عمران: 63] الذين يفسدون في الأرض بإفساد عقائد ضعفاء العباد بالإعراض عن طريق الحق، والإلحاد عن الصراط المستقيم\n\n",
      "translations": []
    },
    {
      "author": "ابن عجيبة",
      "year": "1224",
      "text": "\n آمين، فمن أعرض عن أولياء الله من المنكرين { فإن الله عليم بالمفسدين } ثم دعاهم إلى التوحيد الذي اتفقت عليه سائر الأديان\n\n",
      "translations": []
    }
  ],
  "most_similar_verses": [
    {
      "verse": "10:40",
      "similarity": 0.8185566810791625
    },
    {
      "verse": "89:12",
      "similarity": 0.748101737983205
    },
    {
      "verse": "26:152",
      "similarity": 0.6931636329364171
    },
    {
      "verse": "29:30",
      "similarity": 0.6821292437366587
    },
    {
      "verse": "2:11",
      "similarity": 0.6692383215367134
    }
  ]
}