{
  "chapter": "النجم",
  "text": "افتمرونه على ما يرى",
  "translations": [
    {
      "translation": "Will you dispute with him what he saw?\n",
      "language": "english",
      "translator": ""
    },
    {
      "translation": "Are you, then, going to contend with him regarding what he sees with his eyes?\n",
      "language": "english",
      "translator": ""
    },
    {
      "translation": "Will you then argue with him about what he saw?\n",
      "language": "english",
      "translator": ""
    },
    {
      "translation": "What! So do you dispute with him regarding what he saw?\n",
      "language": "english",
      "translator": ""
    },
    {
      "translation": "Will you then dispute with him about what he saw\n",
      "language": "english",
      "translator": ""
    },
    {
      "translation": "What! do you then dispute with him as to what he saw?\n",
      "language": "english",
      "translator": ""
    },
    {
      "translation": "what, will you dispute with him what he sees?\n",
      "language": "english",
      "translator": ""
    },
    {
      "translation": "Will ye then dispute with him concerning what he seeth?\n",
      "language": "english",
      "translator": ""
    },
    {
      "translation": "Will you then dispute with him as to what he saw?\n",
      "language": "english",
      "translator": ""
    },
    {
      "translation": "Will ye therefore dispute with him concerning that which he hath Seen?\n",
      "language": "english",
      "translator": ""
    },
    {
      "translation": "Will you then dispute with him about what he saw?!\n",
      "language": "english",
      "translator": ""
    },
    {
      "translation": "Will ye then dispute with him concerning what he saw?\n",
      "language": "english",
      "translator": ""
    },
    {
      "translation": "Will you then dispute with him (Muhammad SAW) about what he saw [during the Mi'raj: (Ascent of the Prophet SAW over the seven heavens)].\n",
      "language": "english",
      "translator": ""
    },
    {
      "translation": "What, will you dispute with him about what he sees!\n",
      "language": "english",
      "translator": ""
    },
    {
      "translation": "Will you dispute with him concerning what he saw?\n",
      "language": "english",
      "translator": ""
    },
    {
      "translation": "So will you dispute with him over what he saw?\n",
      "language": "english",
      "translator": ""
    },
    {
      "translation": "[53:12] Will you then dispute with him, will you [then] argue with him and [hope to] overwhelm him, concerning what he saw? — an address to the idolaters who denied the Prophet’s (s) vision of Gabriel.\n",
      "language": "english",
      "translator": ""
    }
  ],
  "commentaries": [
    {
      "author": "ابن عباس",
      "year": "68",
      "text": "",
      "translations": [
        {
          "translation": "621 When the Prophet (pbuh) informed them of what he saw, they disbelieved him. And so Allah said: (Will ye then dispute with him concerning) will you then disbelieve (what he seeth) what Muhammad (pbuh) saw?\n",
          "language": "english",
          "translator": "Mr. Mokrane Guezzou"
        }
      ]
    },
    {
      "author": "زيد بن علي",
      "year": "120",
      "text": "\n",
      "translations": []
    },
    {
      "author": "ابن عربي",
      "year": "638",
      "text": "\n",
      "translations": []
    },
    {
      "author": "الجيلاني",
      "year": "713",
      "text": "\n{ أَ } تنكرون انكشافه وشهوده صلى الله عليه وسلم أيها المحجوبون المحرومون { فَتُمَارُونَهُ } وتجادلون معه على سبيل المراء والمكابرة { عَلَىٰ مَا يَرَىٰ } [النجم: 12] من الذوقيات والوجدانيات التي تأبى عنها عقولكم، وتعمي أبصاركم، ولا يمكن إلقاؤها وكشفها لكم\n\n\n\n",
      "translations": []
    },
    {
      "author": "ابن عجيبة",
      "year": "1224",
      "text": "\n{ أَفتُمارونه } أي: أفتجادلونه، من: المراء، وهو المجادلة، واشتقاقه من: مَرْي الناقة، وهو استخراج لبنها، كأنَّ كل واحد من المتجادلين يَمْري ما عند صاحبه، أي: يستخرجه\n وقُرئ في التواتر: \" أَفَتَمْرُونه \" أي: أفتغلبونه\n ولما فيه من معنى الغلبة، قال تعالى: { على ما يرى } فعدّى بعلى، كما تقول: غلبته على كذا، وقيل: أفتمرونه: أفتجحدونه، يقال: مريته حقّه: جحدته، وتعديته بـ \" على \" على مذهب التضمين، والمعنى: أفتُخاصمونه على ما يرى معانيةً، وحققه باطناً",
      "translations": []
    }
  ]
}