{
  "chapter": "نوح",
  "text": "قال رب انى دعوت قومى ليلا ونهارا",
  "translations": [
    {
      "translation": "He said, 'My Lord, I have called my people night and day",
      "language": "english",
      "translator": ""
    },
    {
      "translation": "He said: \"O Lord, I called my people night and day,\n",
      "language": "english",
      "translator": ""
    },
    {
      "translation": "He said: “My Lord, I called my people by night and by day,\n",
      "language": "english",
      "translator": ""
    },
    {
      "translation": "Noah said, \"My Lord, I have been preaching to my people, night and day,\n",
      "language": "english",
      "translator": ""
    },
    {
      "translation": "He said, “My Lord! I invited my people night and day.”\n",
      "language": "english",
      "translator": ""
    },
    {
      "translation": "He said: O my Lord! Verily, I have called to my people night and day,\n",
      "language": "english",
      "translator": ""
    },
    {
      "translation": "He said: O my Lord! surely I have called my people by night and by day!\n",
      "language": "english",
      "translator": ""
    },
    {
      "translation": "He said; 'My Lord, I have called my people by night and by day,\n",
      "language": "english",
      "translator": ""
    },
    {
      "translation": "He said: My Lord! Lo! I have called unto my people night and day\n",
      "language": "english",
      "translator": ""
    },
    {
      "translation": "He said, \"My Lord! I have called my people night and day\n",
      "language": "english",
      "translator": ""
    },
    {
      "translation": "He said: my Lord! verily have called my people night and day.\n",
      "language": "english",
      "translator": ""
    },
    {
      "translation": "He said, ‘My Lord! Indeed, I have summoned my people night and day\n",
      "language": "english",
      "translator": ""
    },
    {
      "translation": "He said: \"O my Lord! I have called to my People night and day:\n",
      "language": "english",
      "translator": ""
    },
    {
      "translation": "He said: \"O my Lord! Verily, I have called my people night and day (i.e. secretly and openly to accept the doctrine of Islamic Monotheism).\n",
      "language": "english",
      "translator": ""
    },
    {
      "translation": "My Lord' said he, 'night and day I have called my nation,\n",
      "language": "english",
      "translator": ""
    },
    {
      "translation": "He said, “My Lord, I have called my people night and day.\n",
      "language": "english",
      "translator": ""
    },
    {
      "translation": "He said, \"My Lord, indeed I invited my people [to truth] night and day.\n",
      "language": "english",
      "translator": ""
    },
    {
      "translation": "[71:5] He said, ‘My Lord, I have summoned my people night and day, that is to say, continuously without interruption,\n",
      "language": "english",
      "translator": ""
    }
  ],
  "commentaries": [
    {
      "author": "ابن عباس",
      "year": "68",
      "text": "",
      "translations": [
        {
          "translation": "When he despaired of them, after calling them to faith for 950 years, and they refused to believe or heed his advice, (He said: My Lord! Lo! I have called unto my people) to repent and believe in Allah's divine Oneness (night and day) at night and during the day.\n",
          "language": "english",
          "translator": "Mr. Mokrane Guezzou"
        }
      ]
    },
    {
      "author": "زيد بن علي",
      "year": "120",
      "text": "\n",
      "translations": []
    },
    {
      "author": "ابن عربي",
      "year": "638",
      "text": "\n",
      "translations": []
    },
    {
      "author": "الجيلاني",
      "year": "713",
      "text": "\nوبعدما بالغ نوح عليه السلام في دعوتهم وإرشادهم فلم يهتدوا، بل ما زادوا إلاَّ إصراراً وإضراراً، وعناداً واستكباراً { قَالَ } نوح مناجياً إلى ربه على وجه التضرع بعدما بالغوا في الإنكار والاستكبار: { رَبِّ } يا من ربَّاني على الرشد والهداية { إِنِّي دَعَوْتُ قَوْمِي } بمقتضى وحيك وإلهامك عليَّ { لَيْلاً وَنَهَاراً } [نوح: 5] أي: دائماً بلا مطل وتسويف\n\n\n\n",
      "translations": []
    },
    {
      "author": "ابن عجيبة",
      "year": "1224",
      "text": "\nيقول الحق جلّ جلاله: { قال } نوح شاكياً إلى الله تعالى: { رَبِّ إِني دعوتُ قومي } إلى الإيمان والطاعة { ليلاً ونهاراً } دائماً بلا فتور ولا توان، { فلم يَزِدْهُم دعائي إِلاَّ فِراراً } مما دعوتهم إليه، ونسب ذلك إلى دعائه لحصوله عنده، وإن لم يكن في الحقيقة سبباً للفرار، وهو كقوله:\n\n[التوبة:125]، والقرآن لا يكون سبباً لزيادة الرجس، لكن لمّا حصل عنده نُسب إليه، وكان الرجل منهم يذهب بابنه إلى نوح عليه السلام ويقول له: احذر هذا، فلا يعرنّك، فإنّ أبي قد أوصاني بهذا\n هـ",
      "translations": []
    }
  ]
}