{
  "chapter": "الشمس",
  "text": "ونفس وما سوىها",
  "translations": [
    {
      "translation": "and the self and what proportioned it",
      "language": "english",
      "translator": ""
    },
    {
      "translation": "The soul and how it was integrated\n",
      "language": "english",
      "translator": ""
    },
    {
      "translation": "and by the soul and by Him Who perfectly proportioned it,\n",
      "language": "english",
      "translator": ""
    },
    {
      "translation": "and by the soul and that (Power) which designed it\n",
      "language": "english",
      "translator": ""
    },
    {
      "translation": "And by oath of the soul and by oath of Him Who made it proper.\n",
      "language": "english",
      "translator": ""
    },
    {
      "translation": "By Nafs, and Ma Sawwaha (Who apportioned it).\n",
      "language": "english",
      "translator": ""
    },
    {
      "translation": "And the soul and Him Who made it perfect,\n",
      "language": "english",
      "translator": ""
    },
    {
      "translation": "By the soul, and That which shaped it\n",
      "language": "english",
      "translator": ""
    },
    {
      "translation": "And a soul and Him Who perfected it\n",
      "language": "english",
      "translator": ""
    },
    {
      "translation": "by the soul and how He formed it,\n",
      "language": "english",
      "translator": ""
    },
    {
      "translation": "By the soul and Him Who propertioned it,\n",
      "language": "english",
      "translator": ""
    },
    {
      "translation": "by the soul and Him who fashioned it,\n",
      "language": "english",
      "translator": ""
    },
    {
      "translation": "By the Soul, and the proportion and order given to it;\n",
      "language": "english",
      "translator": ""
    },
    {
      "translation": "And by Nafs (Adam or a person or a soul, etc.), and Him Who perfected him in proportion;\n",
      "language": "english",
      "translator": ""
    },
    {
      "translation": "by the soul and Who shaped it\n",
      "language": "english",
      "translator": ""
    },
    {
      "translation": "And the soul and He who proportioned it.\n",
      "language": "english",
      "translator": ""
    },
    {
      "translation": "And [by] the soul and He who proportioned it\n",
      "language": "english",
      "translator": ""
    },
    {
      "translation": "[91:7] and [by] the soul, that is to say, [by] all souls, and the One Who proportioned it, in its created form (mā in all three instances relates to the verbal action, or functions as man, ‘the one who’),\n",
      "language": "english",
      "translator": ""
    }
  ],
  "commentaries": [
    {
      "author": "ابن عباس",
      "year": "68",
      "text": "",
      "translations": [
        {
          "translation": "(And a soul and Him who perfected it) by creating it with two hands, two feet, two eyes, two ears as well as with all the other organs.\n",
          "language": "english",
          "translator": "Mr. Mokrane Guezzou"
        }
      ]
    },
    {
      "author": "زيد بن علي",
      "year": "120",
      "text": "\n",
      "translations": []
    },
    {
      "author": "ابن عربي",
      "year": "638",
      "text": "\n { ونفس } أي: القوة الحيوانية المنطبعة في الروح الحيوانية المسماة باصطلاح أهل الشرع والتصوّف النفس مطلقاً أو الجملة أو النفس الناطقة والحكيم الذي { سوّاها } عدّلها بين جهتي الربوبية والسفالة لا في ظلمة الجسم وكثافته ولا في ضوء الروح ولطافته كما قال:\n",
      "translations": []
    },
    {
      "author": "الجيلاني",
      "year": "713",
      "text": "\n{ وَنَفْسٍ } أي: روح فائضة من عالم الأسماء والصفات على هياكل المسميات وقوابل العلويات والسفليات؛ ليستفيد بتذكر الموطن الأصلي والمنشأ الجبلي { وَمَا سَوَّاهَا } [الشمس: 7] أي: عدَّلها وركَّبها ممتزجة من الآثار العلوية والسفلية\n\n\n\n\nوبعدما سواها وعدلها كذلك { فَأَلْهَمَهَا فُجُورَهَا وَتَقْوَاهَا } [الشمس: 8] على مقتضى ما أودع فيها من الآثار العلوية والسفلية، ثمَّ كلَّفها بما كلفها؛ ليتيمز المحق من المبطل، والضال من الهادي، والكافر من المؤمن؛ تتميماً للحكمة المتقنة البالغة الإلهية وإظهاراً للقدرة الغالبة\n\n\n\n",
      "translations": []
    },
    {
      "author": "ابن عجيبة",
      "year": "1224",
      "text": "\n",
      "translations": []
    }
  ],
  "most_similar_verses": [
    {
      "verse": "87:2",
      "similarity": 0.7077695891371406
    },
    {
      "verse": "26:98",
      "similarity": 0.6901902412169347
    },
    {
      "verse": "36:10",
      "similarity": 0.46542120690747363
    },
    {
      "verse": "32:18",
      "similarity": 0.433971763290509
    },
    {
      "verse": "2:6",
      "similarity": 0.4316661450733357
    }
  ]
}